openwisp_monitoring/__init__.py
openwisp_monitoring/settings.py
openwisp_monitoring/urls.py
openwisp_monitoring/utils.py
openwisp_monitoring/views.py
openwisp_monitoring/check/__init__.py
openwisp_monitoring/check/admin.py
openwisp_monitoring/check/apps.py
openwisp_monitoring/check/checks.py
openwisp_monitoring/check/exceptions.py
openwisp_monitoring/check/models.py
openwisp_monitoring/check/settings.py
openwisp_monitoring/check/tasks.py
openwisp_monitoring/check/utils.py
openwisp_monitoring/check/base/__init__.py
openwisp_monitoring/check/base/models.py
openwisp_monitoring/check/classes/__init__.py
openwisp_monitoring/check/classes/base.py
openwisp_monitoring/check/classes/config_applied.py
openwisp_monitoring/check/classes/data_collected.py
openwisp_monitoring/check/classes/iperf3.py
openwisp_monitoring/check/classes/ping.py
openwisp_monitoring/check/classes/wifi_clients.py
openwisp_monitoring/check/management/__init__.py
openwisp_monitoring/check/management/commands/__init__.py
openwisp_monitoring/check/management/commands/run_checks.py
openwisp_monitoring/check/migrations/0001_initial_squashed_0002_check_unique_together.py
openwisp_monitoring/check/migrations/0003_create_ping.py
openwisp_monitoring/check/migrations/0004_rename_active_to_is_active.py
openwisp_monitoring/check/migrations/0005_create_config_applied.py
openwisp_monitoring/check/migrations/0006_rename_check_check_check_type.py
openwisp_monitoring/check/migrations/0007_create_checks.py
openwisp_monitoring/check/migrations/0008_alter_check_options.py
openwisp_monitoring/check/migrations/0009_add_check_inline_permissions.py
openwisp_monitoring/check/migrations/0010_create_data_collected_check.py
openwisp_monitoring/check/migrations/0011_check_active_object_checks_idx.py
openwisp_monitoring/check/migrations/__init__.py
openwisp_monitoring/check/tests/__init__.py
openwisp_monitoring/check/tests/iperf3_test_utils.py
openwisp_monitoring/check/tests/test_data_collected.py
openwisp_monitoring-1.2.dist-info/licenses/LICENSE
openwisp_monitoring-1.2.dist-info/METADATA
openwisp_monitoring-1.2.dist-info/WHEEL
openwisp_monitoring-1.2.dist-info/top_level.txt
openwisp_monitoring-1.2.dist-info/RECORD
