Metadata-Version: 2.4
Name: openwisp-monitoring
Version: 1.2
Summary: OpenWISP Monitoring
Home-page: http://openwisp.org
Download-URL: https://github.com/openwisp/openwisp-monitoring/releases
Author: OpenWISP
Author-email: support@openwisp.io
License: GPL3
Keywords: django,netjson,networking,openwisp,monitoring
Platform: Platform Independent
Classifier: Development Status :: 5 - Production/Stable
Classifier: Environment :: Web Environment
Classifier: Topic :: Internet :: WWW/HTTP
Classifier: Topic :: System :: Networking
Classifier: Intended Audience :: Developers
Classifier: License :: OSI Approved :: GNU General Public License v3 (GPLv3)
Classifier: Operating System :: OS Independent
Classifier: Framework :: Django
Classifier: Programming Language :: Python :: 2.7
Classifier: Programming Language :: Python :: 3.4
License-File: LICENSE
Requires-Dist: openwisp-controller~=1.2.0
Requires-Dist: influxdb~=5.3.2
Requires-Dist: django-nested-admin~=4.1.4
Requires-Dist: python-dateutil<3.0.0,>=2.7.0
Dynamic: author
Dynamic: author-email
Dynamic: classifier
Dynamic: description
Dynamic: download-url
Dynamic: home-page
Dynamic: keywords
Dynamic: license
Dynamic: license-file
Dynamic: platform
Dynamic: requires-dist
Dynamic: summary
